wagtail_models/__init__.py
wagtail_models/wagtail_models.py
wagtail_models-0.1.dist-info/METADATA
wagtail_models-0.1.dist-info/WHEEL
wagtail_models-0.1.dist-info/top_level.txt
wagtail_models-0.1.dist-info/RECORD
